canederli/__init__.py
canederli/main.py
canederli-0.0.18.dist-info/LICENSE.txt
canederli-0.0.18.dist-info/METADATA
canederli-0.0.18.dist-info/WHEEL
canederli-0.0.18.dist-info/top_level.txt
canederli-0.0.18.dist-info/RECORD
