Metadata-Version: 2.1
Name: canederli
Version: 0.0.18
Summary: Simple tools to quickly get the names of a list of variables out of the lines of code where they are defined.
Home-page: UNKNOWN
Author: tms1991
Author-email: <youremail@email.com>
License: UNKNOWN
Keywords: hardcode,variables,names,labels,strings,list,multiline
Platform: UNKNOWN
Classifier: Development Status :: 3 - Alpha
Classifier: Intended Audience :: Education
Classifier: Programming Language :: Python :: 2
Classifier: Programming Language :: Python :: 3
Classifier: Operating System :: MacOS :: MacOS X
Classifier: Operating System :: Microsoft :: Windows
License-File: LICENSE.txt
